halutz/__init__.py
halutz/class_factory.py
halutz/client.py
halutz/indexer.py
halutz/request.py
halutz/request_factory.py
halutz/utils.py
halutz-0.5.1.dist-info/METADATA
halutz-0.5.1.dist-info/RECORD
halutz-0.5.1.dist-info/WHEEL
halutz-0.5.1.dist-info/top_level.txt
