Metadata-Version: 2.1
Name: halutz
Version: 0.5.1
Summary: Halutz is a python library for Swagger, inspired by working with network engineers getting started with Python.
Home-page: https://github.com/jeremyschulman/halutz
Author: Jeremy Schulman
Author-email: nwkautomaniac@gmail.com
License: MIT
Keywords: serialization,rest,json,api,marshal,marshalling,deserialization,validation,schema,jsonschema,swagger,openapi,networking,automation
Platform: UNKNOWN
Classifier: Development Status :: 4 - Beta
Classifier: Intended Audience :: Developers
Classifier: License :: OSI Approved :: MIT License
Classifier: Programming Language :: Python :: 2.7
Classifier: Programming Language :: Python :: 3.6
Requires-Dist: bravado
Requires-Dist: first
Requires-Dist: inflection
Requires-Dist: jsonschema
Requires-Dist: msgpack
Requires-Dist: python-jsonschema-objects
Requires-Dist: six
Requires-Dist: bidict
